Workbook

Sheet Inputs
A1: Assumption | B1: Value | C1: Notes
A2: Risk-free rate | B2: 0.04 | C2: US 10-year Treasury
A3: Market risk premium | B3: 0.06 | C3: Standard US equity premium
A4: Beta | B4: 0.55 | C4: From Yahoo Finance (approx.)
A5: Cost of debt (pre-tax) | B5: 0.035 | C5: Approx. from KO filings
A6: Tax rate | B6: 0.21 | C6: US corporate tax
A7: Terminal growth | B7: 0.02 | C7: Mature beverage company
A8: WACC

Sheet Historical
A1: Metric | B1: 2019 | C1: 2020 | D1: 2021 | E1: 2022 | F1: 2023
A2: Revenue | B2: 37266 | C2: 33014 | D2: 38655 | E2: 43004 | F2: 45754
A3: COGS | B3: 14619 | C3: 13433 | D3: 15278 | E3: 16914 | F3: 17528
A4: Gross Profit
A5: Operating Expenses | B5: 15266 | C5: 12736 | D5: 14723 | E5: 15771 | F5: 16535
A6: EBIT | B6: 10087 | C6: 9215 | D6: 10303 | E6: 11054 | F6: 11697
A7: Depreciation & Amortization | B7: 1216 | C7: 1234 | D7: 1330 | E7: 1408 | F7: 1466
A8: CapEx | B8: 1281 | C8: 1186 | D8: 1330 | E8: 1629 | F8: 1813
A9: Change in Working Capital | B9: -187 | C9: 402 | D9: -1025 | E9: 476 | F9: -394
A10: Tax Expense | B10: 2199 | C10: 1637 | D10: 2581 | E10: 2871 | F10: 2978
A11: Net Income | B11: 8920 | C11: 7747 | D11: 9771 | E11: 9542 | F11: 10711
A12: FCFF

Sheet Projections
A1: Years | B1: 2024E | C1: 2025E | D1: 2026E | E1: 2027E | F1: 2028E
A2: Revenue | B2: =Historical!F2 * (1 + B3) -> 48041.7 | C2: =B2 * (1 + C3) -> 49963.368 | D2: =C2 * (1 + D3) -> 51712.086 | E2: =D2 * (1 + E3) -> 53263.448 | F2: =E2 * (1 + F3) -> 54595.035
A3: % Growth | B3: 0.05 | C3: 0.04 | D3: 0.035 | E3: 0.03 | F3: 0.025
A4: COGS | B4: =B2 * 0.38 -> 18255.846 | C4: =C2 * 0.38 -> 18986.08 | D4: =D2 * 0.38 -> 19650.593 | E4: =E2 * 0.38 -> 20240.11 | F4: =F2 * 0.38 -> 20746.113 | M4: COGS | N4: 0.38
A5: Operating Expenses | B5: =B2 * 0.35 -> 16814.595 | C5: =C2 * 0.35 -> 17487.179 | D5: =D2 * 0.35 -> 18099.23 | E5: =E2 * 0.35 -> 18642.207 | F5: =F2 * 0.35 -> 19108.262 | M5: GP | N5: 0.35
A6: EBIT | B6: =B2 - B4 - B5 -> 12971.259 | C6: =C2 - C4 - C5 -> 13490.109 | D6: =D2 - D4 - D5 -> 13962.263 | E6: =E2 - E4 - E5 -> 14381.131 | F6: =F2 - F4 - F5 -> 14740.659 | M6: OPEX | N6: 0.35
A7: Tax | B7: =B6 * 0.21 -> 2723.9644 | C7: =C6 * 0.21 -> 2832.923 | D7: =D6 * 0.21 -> 2932.0753 | E7: =E6 * 0.21 -> 3020.0375 | F7: =F6 * 0.21 -> 3095.5385
A8: Depreciation | B8: =B2 * 0.03 -> 1441.251 | C8: =C2 * 0.03 -> 1498.901 | D8: =D2 * 0.03 -> 1551.3626 | E8: =E2 * 0.03 -> 1597.9035 | F8: =F2 * 0.03 -> 1637.851 | M8: Tax rate | N8: 0.21
A9: CapEx | B9: =B2 * 0.035 -> 1681.4595 | C9: =C2 * 0.035 -> 1748.7179 | D9: =D2 * 0.035 -> 1809.923 | E9: =E2 * 0.035 -> 1864.2207 | F9: =F2 * 0.035 -> 1910.8262 | M9: DEPRECIATION | N9: 0.3
A10: Change in Working Capital | B10: =- B2 * 0.01 -> -480.417 | C10: =- C2 * 0.01 -> -499.63368 | D10: =- D2 * 0.01 -> -517.12086 | E10: =- E2 * 0.01 -> -532.63448 | F10: =- F2 * 0.01 -> -545.95035 | M10: CAPEX | N10: 0.35
A11: FCFF | B11: =B6*(1-0.21) + B8 - B9 - B10 -> 10487.503 | C11: =C6*(1-0.21) + C8 - C9 - C10 -> 10907.003 | D11: =D6*(1-0.21) + D8 - D9 - D10 -> 11288.748 | E11: =E6*(1-0.21) + E8 - E9 - E10 -> 11627.411 | F11: =F6*(1-0.21) + F8 - F9 - F10 -> 11918.096 | M11: WC | N11: 0

Sheet DCF
A1: Year | B1: 2024E | C1: 2025E | D1: 2026E | E1: 2027E | F1: 2028E
A2: FCFF | B2: =Projections!B11 -> 10487.503 | C2: =Projections!C11 -> 10907.003 | D2: =Projections!D11 -> 11288.748 | E2: =Projections!E11 -> 11627.411 | F2: =Projections!F11 -> 11918.096
A3: Discount Factor | B3: =1 / (1 + 0.06)^1 -> 0.94339623 | C3: =1 / (1 + 0.06)^2 -> 0.88999644 | D3: =1 / (1 + 0.06)^3 -> 0.83961928 | E3: =1 / (1 + 0.06)^4 -> 0.79209366 | F3: =1 / (1 + 0.06)^5 -> 0.74725817
A4: Present Value of FCFF | B4: =B2 * B3 -> 9893.8709 | C4: =C2 * C3 -> 9707.194 | D4: =D2 * D3 -> 9478.2508 | E4: =E2 * E3 -> 9209.9984 | F4: =F2 * F3 -> 8905.8947
A5: Terminal Value | F5: =F2 * (1 + 0.02) / (0.06 - 0.02) -> 303911.45
A6: Present Value of Terminal Value | F6: =F5 * F3 -> 227100.31
A7: Enterprise Value | F7: =SUM(B4:F4) + F6 -> 274295.52
A8: Less: Net Debt | F8: 38000
A9: Equity Value | F9: =F7 - F8 -> 236295.52
A10: Shares Outstanding | F10: 4320
A11: Intrinsic Share Price | F11: =F9 / F10 -> 54.698038

Sheet Sensitivity
B1: g=1.0% | C1: g=1.5% | D1: g=2.0% | E1: g=2.5% | F1: g=3.0%
A2: WACC 6.5%
A3: WACC 7.0%
A4: WACC 7.5%
A5: WACC 8.0%
A6: WACC 8.5%

Sheet Comps
A1: Company | B1: Ticker | C1: Market Cap | D1: EV | E1: Revenue | F1: EBITDA | G1: EV/EBITDA | H1: P/E
A2: PepsiCo | B2: PEP | C2: 230000 | D2: 275000 | E2: 91000 | F2: 15400 | G2: 17.9 | H2: 24
A3: Keurig Dr Pepper | B3: KDP | C3: 46000 | D3: 61000 | E3: 14800 | F3: 4100 | G3: 14.9 | H3: 19
A4: Monster Beverage | B4: MNST | C4: 52000 | D4: 50000 | E4: 7100 | F4: 2350 | G4: 21.3 | H4: 34
A5: Celsius Holdings | B5: CELH | C5: 15000 | D5: 14500 | E5: 1600 | F5: 200 | G5: 72.5 | H5: 70
A6: Coca-Cola Femsa | B6: KOF | C6: 17000 | D6: 20000 | E6: 13000 | F6: 2350 | G6: 8.5 | H6: 18
G7: =MEDIAN(G2:G6) -> 17.9 | H7: =MEDIAN(H2:H6) -> 24

Sheet Summary
A1: Valuation Output | B1: DCF valuation
B2: Enterprise Value: | C2: =DCF!F7 -> 274295.52
B3: Net Debt: | C3: =DCF!F8 -> 38000
B4: Equity Value: | C4: =DCF!F9 -> 236295.52
B5: Shares Outstanding: | C5: =DCF!F10 -> 4320
B6: Intrinsic Share Price (DCF): | C6: =DCF!F11 -> 54.698038
B8: Comps Valuation
B9: EV/EBITDA Median: | C9: 17.9
B10: Implied EV: | C10: =13500 * 17.9 -> 241650
B11: Implied Equity Value: | C11: =C10 - 38000 -> 203650
B12: Implied Share Price (EV/EBITDA): | C12: =C11 / 4320 -> 47.141204
B14: P/E Median: | C14: 24
B15: Implied Equity Value: | C15: =10000 * 24 -> 240000
B16: Implied Share Price (P/E): | C16: =C15 / 4320 -> 55.555556
B18: Final Target Price: | C18: =AVERAGE( C6, C13, C16 ) -> 55.126797
A20: Charts
B21: Revenue Chart
B37: FCFF Chart
B53: Valuation comparison chart
B54: Method | C54: Value
B55: DCF Price | C55: 54.698
B56: EV/EBITDA Price | C56: 47.141
B57: P/E Price | C57: 55.556
B68: Value Breakdown
B69: PV of FCFF | C69: =SUM(DCF!B4:F4) -> 47195.209
B70: PV of Terminal Value | C70: =DCF!F6 -> 227100.31
A85: Investment Thesis | B85: Coca-Cola is a resilient global leader in the non-alcoholic beverage sector with unmatched brand equity, extensive global distribution, and consistent pricing power. The business delivers stable free cash flows due to its asset-light bottling strategy and strong operating margins. KO has proven ability to pass on cost inflation, maintain volume through economic cycles, and expand margins through disciplined cost management. While growth is moderate, the company remains one of the strongest defensive compounders in the market.
A86: Risks | B86: Coca-Cola’s growth is slowing in developed markets. More people are becoming health-conscious, which affects sugary drinks. The company earns a lot from outside the US, so currency changes can impact results. Costs of raw materials like sugar and aluminum can rise unexpectedly. Strong competition from PepsiCo and newer energy drink brands.
A87: Final Recommendation | B87: HOLD
